vndb_dl/__init__.py
vndb_dl/arg_parser.py
vndb_dl/main.py
vndb_dl/vn.py
vndb_dl-0.1.0.dist-info/LICENSE
vndb_dl-0.1.0.dist-info/METADATA
vndb_dl-0.1.0.dist-info/WHEEL
vndb_dl-0.1.0.dist-info/entry_points.txt
vndb_dl-0.1.0.dist-info/top_level.txt
vndb_dl-0.1.0.dist-info/RECORD
