Metadata-Version: 2.1
Name: vndb-dl
Version: 0.1.0
Summary: Download visual novel metadata and screenshots from vndb.org
Home-page: https://github.com/xy2iii/vndb_dl
Author: xy2_
Author-email: xy2trezatreza@gmail.com
License: UNKNOWN
Platform: UNKNOWN
Classifier: Programming Language :: Python :: 3
Classifier: License :: OSI Approved :: GNU General Public License v3 (GPLv3)
Classifier: Operating System :: OS Independent
Requires-Dist: beautifulsoup4
Requires-Dist: requests
